fortran_namelist/__init__.py
wrf4g/__init__.py
wrf4g/_static_version.py
wrf4g/_version.py
wrf4g/config.py
wrf4g/core.py
wrf4g/db.py
wrf4g/orm.py
wrf4g/slurm_cesga.py
wrf4g/wrapper.py
wrf4g/commands/__init__.py
wrf4g/commands/conf.py
wrf4g/commands/exp.py
wrf4g/commands/host.py
wrf4g/commands/id.py
wrf4g/commands/job.py
wrf4g/commands/rea.py
wrf4g/commands/resource.py
wrf4g/commands/start.py
wrf4g/commands/status.py
wrf4g/commands/stop.py
wrf4g/commands/syncdb.py
wrf4g/commands/vcp.py
wrf4g/data/etc/db.conf
wrf4g/data/etc/gwrc
wrf4g/data/etc/wrf4g.db
wrf4g/data/etc/wrf4g_wrapper.sh
wrf4g/data/etc/templates/experiments/default/experiment.wrf4g
wrf4g/data/etc/templates/experiments/physics/experiment.wrf4g
wrf4g/data/etc/templates/experiments/single/experiment.wrf4g
wrf4g/data/etc/templates/namelist/namelist.input-3.2
wrf4g/data/etc/templates/namelist/namelist.input-3.2.1
wrf4g/data/etc/templates/namelist/namelist.input-3.3
wrf4g/data/etc/templates/namelist/namelist.input-3.3.1
wrf4g/data/etc/templates/namelist/namelist.input-3.4
wrf4g/data/etc/templates/namelist/namelist.input-3.4.1
wrf4g/data/etc/templates/namelist/namelist.input-3.5
wrf4g/data/etc/templates/namelist/namelist.input-3.5.1
wrf4g/data/etc/templates/namelist/namelist.input-3.6
wrf4g/data/etc/templates/namelist/namelist.input-3.6.1
wrf4g/data/etc/templates/namelist/namelist.input-3.7
wrf4g/data/etc/templates/namelist/namelist.input-3.7.1
wrf4g/data/etc/templates/namelist/namelist.input-3.8
wrf4g/data/etc/templates/namelist/namelist.input-3.8.1
wrf4g/data/etc/templates/namelist/namelist.input-4.1
wrf4g/data/etc/templates/namelist/namelist.input-4.1.2
wrf4g/data/etc/templates/namelist/namelist.input-4.2.2
wrf4g/data/wn/bin/postprocessor.ALLSTDPLEVS
wrf4g/data/wn/bin/postprocessor.CLIMATICBASIC
wrf4g/data/wn/bin/postprocessor.PBL
wrf4g/data/wn/bin/postprocessor.SFC
wrf4g/data/wn/bin/preprocessor.CNRM
wrf4g/data/wn/bin/preprocessor.ECHAM5
wrf4g/data/wn/bin/preprocessor.ECMWF
wrf4g-3.1.0.dist-info/LICENSE
wrf4g-3.1.0.dist-info/METADATA
wrf4g-3.1.0.dist-info/WHEEL
wrf4g-3.1.0.dist-info/top_level.txt
wrf4g-3.1.0.dist-info/RECORD
