Metadata-Version: 2.1
Name: wrf4g
Version: 3.1.0
Summary: WRF for Grid (WRF4G) is a framework for the execution and monitoring of the WRF Modelling System.
Home-page: https://meteo.unican.es/trac/wiki/WRF4G2.0
Author: Santander Meteorology Group
Author-email: meteo@unican.es
License: European Union Public License 1.1
Platform: UNKNOWN
Classifier: Intended Audience :: Science/Research
Classifier: Programming Language :: Python
Classifier: Topic :: Scientific/Engineering
Classifier: Topic :: Office/Business :: Scheduling
Classifier: Programming Language :: Python :: 3
Classifier: Programming Language :: Python :: 3.5
Classifier: Programming Language :: Python :: 3.6
Classifier: Programming Language :: Python :: 3.7
Classifier: Programming Language :: Python :: 3.8
Classifier: Programming Language :: Python :: 3.9
Requires-Python: >=3.5
Requires-Dist: drm4g
Requires-Dist: python-dateutil
Requires-Dist: requests
Requires-Dist: six
Requires-Dist: sqlalchemy
